{
  "groupName" : "21ПСА-6",
  "daySchedules" : [ {
    "day" : "MONDAY",
    "lessons" : [ {
      "number" : 0,
      "name" : null,
      "teacher" : null,
      "place" : null
    }, {
      "number" : 1,
      "name" : "Физ-ра",
      "teacher" : "Гильманов Р.А.",
      "place" : null
    }, {
      "number" : 2,
      "name" : "Уголовное право",
      "teacher" : "Имаева А.В.",
      "place" : "305"
    }, {
      "number" : 3,
      "name" : "Уголовное право",
      "teacher" : "Имаева А.В.",
      "place" : "305"
    }, {
      "number" : 4,
      "name" : "Основы философии",
      "teacher" : "Каримова И.Р.",
      "place" : "336"
    }, {
      "number" : 5,
      "name" : null,
      "teacher" : null,
      "place" : null
    }, {
      "number" : 6,
      "name" : null,
      "teacher" : null,
      "place" : null
    } ]
  }, {
    "day" : "TUESDAY",
    "lessons" : [ {
      "number" : 0,
      "name" : null,
      "teacher" : null,
      "place" : null
    }, {
      "number" : 1,
      "name" : null,
      "teacher" : null,
      "place" : null
    }, {
      "number" : 2,
      "name" : "Уголовное право",
      "teacher" : "Имаева А.В.",
      "place" : "216"
    }, {
      "number" : 3,
      "name" : "Уголовное право",
      "teacher" : "Имаева А.В.",
      "place" : "216"
    }, {
      "number" : 4,
      "name" : "Управл персоналом",
      "teacher" : "Алибаева Р.Р.",
      "place" : "305"
    }, {
      "number" : 5,
      "name" : null,
      "teacher" : null,
      "place" : null
    }, {
      "number" : 6,
      "name" : null,
      "teacher" : null,
      "place" : null
    } ]
  }, {
    "day" : "WEDNESDAY",
    "lessons" : [ {
      "number" : 0,
      "name" : null,
      "teacher" : null,
      "place" : null
    }, {
      "number" : 1,
      "name" : null,
      "teacher" : null,
      "place" : null
    }, {
      "number" : 2,
      "name" : null,
      "teacher" : null,
      "place" : null
    }, {
      "number" : 3,
      "name" : "Уголовный процесс",
      "teacher" : "Сагидуллин Д.Р.",
      "place" : "312"
    }, {
      "number" : 4,
      "name" : "Уголовный процесс",
      "teacher" : "Сагидуллин Д.Р.",
      "place" : "312"
    }, {
      "number" : 5,
      "name" : "Граж процесс",
      "teacher" : "Маликов М.Г.",
      "place" : "216"
    }, {
      "number" : 6,
      "name" : "Основы статистики",
      "teacher" : "Попова И.А.",
      "place" : "343"
    } ]
  }, {
    "day" : "THURSDAY",
    "lessons" : [ {
      "number" : 0,
      "name" : null,
      "teacher" : null,
      "place" : null
    }, {
      "number" : 1,
      "name" : "Ин яз",
      "teacher" : "Сорокина Э.Г.",
      "place" : "324"
    }, {
      "number" : 2,
      "name" : "Конст право",
      "teacher" : "Альмухаметова Г.А.",
      "place" : "117"
    }, {
      "number" : 3,
      "name" : "Конст право",
      "teacher" : "Альмухаметова Г.А.",
      "place" : "117"
    }, {
      "number" : 4,
      "name" : null,
      "teacher" : null,
      "place" : null
    }, {
      "number" : 5,
      "name" : null,
      "teacher" : null,
      "place" : null
    }, {
      "number" : 6,
      "name" : null,
      "teacher" : null,
      "place" : null
    } ]
  }, {
    "day" : "FRIDAY",
    "lessons" : [ {
      "number" : 0,
      "name" : null,
      "teacher" : null,
      "place" : null
    }, {
      "number" : 1,
      "name" : "Труд право",
      "teacher" : "Ахметова Э.Р.",
      "place" : "110"
    }, {
      "number" : 2,
      "name" : "Админ право",
      "teacher" : "Султанов У.З.",
      "place" : "111"
    }, {
      "number" : 3,
      "name" : null,
      "teacher" : null,
      "place" : null
    }, {
      "number" : 4,
      "name" : null,
      "teacher" : null,
      "place" : null
    }, {
      "number" : 5,
      "name" : null,
      "teacher" : null,
      "place" : null
    }, {
      "number" : 6,
      "name" : null,
      "teacher" : null,
      "place" : null
    } ]
  }, {
    "day" : "SATURDAY",
    "lessons" : [ {
      "number" : 0,
      "name" : "МДК.04.01",
      "teacher" : "Ардуванова Д.Р.",
      "place" : "1Ф"
    }, {
      "number" : 1,
      "name" : "МДК.04.02",
      "teacher" : "Ардуванова Д.Р.",
      "place" : "1Ф"
    }, {
      "number" : 2,
      "name" : null,
      "teacher" : null,
      "place" : null
    }, {
      "number" : 3,
      "name" : null,
      "teacher" : null,
      "place" : null
    }, {
      "number" : 4,
      "name" : null,
      "teacher" : null,
      "place" : null
    }, {
      "number" : 5,
      "name" : null,
      "teacher" : null,
      "place" : null
    }, {
      "number" : 6,
      "name" : null,
      "teacher" : null,
      "place" : null
    } ]
  }, {
    "day" : "SUNDAY",
    "lessons" : [ ]
  } ]
}